.gitattributes
.gitignore
LICENSE
MANIFEST.in
README.md
README.txt
setup.cfg
setup.py
versioneer.py
bb_astromodels/__init__.py
bb_astromodels/_version.py
bb_astromodels.egg-info/PKG-INFO
bb_astromodels.egg-info/SOURCES.txt
bb_astromodels.egg-info/dependency_links.txt
bb_astromodels.egg-info/requires.txt
bb_astromodels.egg-info/top_level.txt
bb_astromodels/data/__init__.py
bb_astromodels/data/abundance/abundances.dat
bb_astromodels/data/ionized/mansig.fits
bb_astromodels/utils/__init__.py
bb_astromodels/utils/cache.py
bb_astromodels/utils/data_files.py
bb_astromodels/utils/numba_functions.py
bb_astromodels/xray/__init__.py
bb_astromodels/xray/absorption.py
notebooks/bb_astromodels_show.ipynb