Metadata-Version: 2.1
Name: bb-astromodels
Version: 0.1.2
Summary: Some additional models for astromodels
Home-page: https://github.com/BjoernBiltzinger/bb_astromodels
Author: Björn Biltzinger
Author-email: bbiltzing@mpe.mpg.de
License: GPL-2+
Project-URL: Bug Tracker, https://github.com/BjoernBiltzinger/bb_astromodels/issues
Project-URL: Source Code, https://github.com/BjoernBiltzinger/bb_astromodels
Platform: UNKNOWN
Classifier: Development Status :: 2 - Pre-Alpha
Classifier: Environment :: Console
Classifier: Intended Audience :: Science/Research
Classifier: License :: OSI Approved :: GNU General Public License v2 or later (GPLv2+)
Classifier: Operating System :: POSIX
Classifier: Programming Language :: Python :: 3.5
Classifier: Programming Language :: Python :: 3.6
Classifier: Programming Language :: Python :: 3.7
Classifier: Programming Language :: Python :: 3.8
Classifier: Topic :: Scientific/Engineering :: Physics
